music_drummer/__init__.py
music_drummer/music_drummer.py
music_drummer-0.3.16.dist-info/licenses/LICENSE
music_drummer-0.3.16.dist-info/METADATA
music_drummer-0.3.16.dist-info/WHEEL
music_drummer-0.3.16.dist-info/top_level.txt
music_drummer-0.3.16.dist-info/RECORD
