Metadata-Version: 2.4
Name: music_drummer
Version: 0.3.16
Summary: Glorified Metronome
Author-email: Gene Boggs <gene.boggs@gmail.com>
License:                     GNU GENERAL PUBLIC LICENSE
Project-URL: Homepage, https://github.com/ology/python-music-drummer
Project-URL: Repository, https://github.com/ology/python-music-drummer.git
Project-URL: Issues, https://github.com/ology/python-music-drummer/issues
Classifier: Development Status :: 2 - Pre-Alpha
Classifier: Programming Language :: Python
Classifier: Programming Language :: Python :: 3
Classifier: Programming Language :: Python :: 3.9
Classifier: Programming Language :: Python :: 3.10
Classifier: Programming Language :: Python :: 3.11
Classifier: Programming Language :: Python :: 3.12
Requires-Python: >=3.9
License-File: LICENSE
Requires-Dist: music21
Requires-Dist: mido
Dynamic: license-file
